HoyoSophonDL/__init__.py
HoyoSophonDL/__main__.py
HoyoSophonDL/client.py
HoyoSophonDL/config.py
HoyoSophonDL/download.py
HoyoSophonDL/gui.py
HoyoSophonDL/help.py
HoyoSophonDL/parser.py
HoyoSophonDL/proto/SophonManifestProto.py
HoyoSophonDL/proto/SophonPatchProto.py
HoyoSophonDL/proto/__init__.py
HoyoSophonDL/structs/Assets.py
HoyoSophonDL/structs/GamesInfo.py
HoyoSophonDL/structs/SophonManifest.py
HoyoSophonDL/structs/__init__.py
hoyosophondl-1.0.4.dist-info/licenses/LICENSE
hoyosophondl-1.0.4.dist-info/METADATA
hoyosophondl-1.0.4.dist-info/WHEEL
hoyosophondl-1.0.4.dist-info/entry_points.txt
hoyosophondl-1.0.4.dist-info/top_level.txt
hoyosophondl-1.0.4.dist-info/RECORD
