Metadata-Version: 2.4
Name: HoyoSophonDL
Version: 1.0.4
Summary: HoyoSophonDL CLI is a Python-based reimplementation of HoYoPlay’s downloader logic. It allows users to list, validate, and download game assets directly from HoYoPlay manifests, with support for multi-threading, resumable downloads, and optional GUI mode.
Home-page: https://github.com/Jo0X01/HoyoSophonDL
Author: Mr.Jo0x01
Author-email: 
Classifier: Programming Language :: Python :: 3.11
Classifier: License :: OSI Approved :: GNU General Public License v3 (GPLv3)
Classifier: Operating System :: Microsoft :: Windows
Classifier: Operating System :: POSIX :: Linux
Classifier: Operating System :: MacOS
Classifier: Topic :: Games/Entertainment
Classifier: Topic :: Software Development :: Libraries :: Application Frameworks
Requires-Python: >=3.9
License-File: LICENSE
Requires-Dist: certifi>=2025.10.5
Requires-Dist: charset-normalizer>=3.4.3
Requires-Dist: colorama>=0.4.6
Requires-Dist: idna>=3.10
Requires-Dist: loguru>=0.7.3
Requires-Dist: lz4>=4.4.4
Requires-Dist: markdown-it-py>=4.0.0
Requires-Dist: mdurl>=0.1.2
Requires-Dist: packaging>=25.0
Requires-Dist: protobuf>=6.32.1
Requires-Dist: Pygments>=2.19.2
Requires-Dist: requests>=2.32.5
Requires-Dist: rich>=14.1.0
Requires-Dist: urllib3>=2.5.0
Requires-Dist: zstandard>=0.25.0
Requires-Dist: python-magic>=0.4.27
Provides-Extra: gui
Requires-Dist: PyQt6>=6.9.1; extra == "gui"
Requires-Dist: PyQt6-Qt6>=6.9.2; extra == "gui"
Requires-Dist: PyQt6_sip>=13.10.2; extra == "gui"
Dynamic: author
Dynamic: classifier
Dynamic: description
Dynamic: description-content-type
Dynamic: home-page
Dynamic: license-file
Dynamic: provides-extra
Dynamic: requires-dist
Dynamic: requires-python
Dynamic: summary
